{"2023-6":[{"title":"test 11","date":"2023-06-06T09:47:57.000Z","link":"/2023/06/06/My-New-Blog-Post/"}],"2024-6":[{"title":"搭建个人网站","date":"2024-06-06T09:47:57.000Z","link":"/2024/06/06/test/"},{"title":"搭建个人网站","date":"2024-06-06T09:47:57.000Z","link":"/2024/06/06/搭建个人网站/"}],"2024-7":[{"title":"Cherry键盘驯服记（Mac篇）","date":"2024-07-19T09:04:17.000Z","link":"/2024/07/19/Cherry键盘驯服记/"},{"title":"添加搜索框","date":"2024-07-22T13:52:39.000Z","link":"/2024/07/22/添加搜索框/"},{"title":"Hexo样式管理","date":"2024-07-23T10:12:36.000Z","link":"/2024/07/23/Hexo样式管理/"},{"title":"My Post","date":"2024-07-23T16:00:00.000Z","link":"/2024/07/24/test1/"}]}